stf/__init__.py
stf/activations.py
stf/configuration_utils.py
stf/convert_slow_tokenizer.py
stf/debug_utils.py
stf/dependency_versions_check.py
stf/dependency_versions_table.py
stf/dynamic_module_utils.py
stf/hf_argparser.py
stf/hyperparameter_search.py
stf/modelcard.py
stf/modeling_outputs.py
stf/modeling_utils.py
stf/optimization.py
stf/pytorch_utils.py
stf/tokenization_utils.py
stf/tokenization_utils_base.py
stf/tokenization_utils_fast.py
stf/trainer.py
stf/trainer_callback.py
stf/trainer_pt_utils.py
stf/trainer_utils.py
stf/training_args.py
stf/data/__init__.py
stf/data/data_collator.py
stf/generation/__init__.py
stf/generation/beam_constraints.py
stf/generation/beam_search.py
stf/generation/configuration_utils.py
stf/generation/logits_process.py
stf/generation/stopping_criteria.py
stf/generation/streamers.py
stf/generation/utils.py
stf/integrations/__init__.py
stf/integrations/bitsandbytes.py
stf/integrations/deepspeed.py
stf/integrations/integration_utils.py
stf/integrations/peft.py
stf/models/__init__.py
stf/models/auto/__init__.py
stf/models/auto/auto_factory.py
stf/models/auto/configuration_auto.py
stf/models/auto/modeling_auto.py
stf/models/bert/__init__.py
stf/models/bert/tokenization_bert.py
stf/models/bert/tokenization_bert_fast.py
stf/utils/__init__.py
stf/utils/doc.py
stf/utils/dummy_pt_objects.py
stf/utils/generic.py
stf/utils/hub.py
stf/utils/import_utils.py
stf/utils/logging.py
stf/utils/peft_utils.py
stf/utils/quantization_config.py
stf/utils/versions.py
stf_test1-0.0.4.dist-info/LICENSE
stf_test1-0.0.4.dist-info/METADATA
stf_test1-0.0.4.dist-info/WHEEL
stf_test1-0.0.4.dist-info/top_level.txt
stf_test1-0.0.4.dist-info/RECORD
