Metadata-Version: 2.1
Name: stf-test1
Version: 0.0.4
Summary: stf
Author-email: linzai <xxxx@qq.com>
License: Copyright 2018- The Hugging Face team. All rights reserved.
Classifier: Programming Language :: Python :: 3
Classifier: License :: OSI Approved :: MIT License
Classifier: Operating System :: OS Independent
Requires-Python: >=3.8.10
License-File: LICENSE
Requires-Dist: huggingface-hub ==0.16.4
Requires-Dist: safetensors ==0.4.1
Requires-Dist: accelerate ==0.25.0
Requires-Dist: tokenizers ==0.14.0
Requires-Dist: datasets ==2.8.0
